paginator.py
simple_embed_pagination-1.0.2.dist-info/LICENSE
simple_embed_pagination-1.0.2.dist-info/METADATA
simple_embed_pagination-1.0.2.dist-info/WHEEL
simple_embed_pagination-1.0.2.dist-info/top_level.txt
simple_embed_pagination-1.0.2.dist-info/RECORD
